pydns/__init__.py
pydns/answer.py
pydns/content.py
pydns/enum.py
pydns/exceptions.py
pydns/flags.py
pydns/message.py
pydns/py.typed
pydns/question.py
pydns/client/__init__.py
pydns/client/https.py
pydns/client/standard.py
pydns/edns/__init__.py
pydns/edns/record.py
pydns/server/__init__.py
pydns/server/server.py
pydns/server/backend/__init__.py
pydns/server/backend/cache.py
pydns/server/backend/forwarder.py
pydns/server/backend/memory.py
pydns/server/backend/ruleset/__init__.py
pydns/server/backend/ruleset/database.py
pydns/server/backend/ruleset/parser.py
pydns/server/backend/ruleset/wildcard.py
pydns/tests/__init__.py
pydns/tests/client.py
pydns/tests/message.py
pydns3-0.0.10.dist-info/LICENSE
pydns3-0.0.10.dist-info/METADATA
pydns3-0.0.10.dist-info/WHEEL
pydns3-0.0.10.dist-info/top_level.txt
pydns3-0.0.10.dist-info/RECORD
